adder.vhd
LIBRARY IEEE;
USE IEEE.STD_LOGIC_1164.ALL;
USE IEEE.NUMERIC_STD.ALL;

LIBRARY CombinationalTools;
USE CombinationalTools.bus_mux_pkg.ALL;
LIBRARY SequentialTools;
USE SequentialTools.ALL;

ENTITY adder IS
	GENERIC 
	(
		word_size : INTEGER :=32
	);
	PORT
	(
		op_0 : IN STD_LOGIC_VECTOR(word_size-1 DOWNTO 0);
		op_1 : IN STD_LOGIC_VECTOR(word_size-1 DOWNTO 0);
		sum : OUT STD_LOGIC_VECTOR(word_size-1 DOWNTO 0);
		C : OUT STD_LOGIC
	);
END ENTITY adder;

architecture comp_adder of adder Is
    Signal carry : STD_LOGIC_VECTOR(word_size-1 DOWNTO 0);
begin
    sum(0) <= op_0(0) xor op_1(0);
    carry(0) <= op_0(0) and op_1(0);
    
    GEN_ADD:
    for i in 1 to 31 generate 
        sum(i) <= op_0(i) xor op_1(i) xor carry(i-1);
        carry(i) <= (op_0(i) and op_1(i)) or (op_0(i) and carry(i-1)) or (op_1(i) and carry(i-1));
    end generate GEN_ADD;
    
    C <= carry(31);
end architecture comp_adder;

testbench_adder.vhd
LIBRARY IEEE;
USE IEEE.STD_LOGIC_1164.ALL;
USE IEEE.NUMERIC_STD.ALL;
use ieee.std_logic_arith.all;

ENTITY test IS
END ENTITY;

Architecture arc of test is
    Constant word_size : INTEGER :=32;
    Signal op_0 : STD_LOGIC_VECTOR(word_size-1 DOWNTO 0);
    Signal op_1 : STD_LOGIC_VECTOR(word_size-1 DOWNTO 0);
    Signal sum : STD_LOGIC_VECTOR(word_size-1 DOWNTO 0);
    Signal C : STD_LOGIC;
begin
    inst_add : entity work.adder(comp_adder) generic Map (word_size) Port Map(op_0,op_1,sum,C);
    Process
    Begin
        op_0 <= conv_std_logic_vector(1,op_0'length);
        --Au dernier tour de boucle la somme vaut 2**32 donc trop grand pour le vecteur, une retenue est retourné.
        for i in 0 to word_size loop
            op_1 <= conv_std_logic_vector((2**i)-1,op_1'length);
            wait for 5 ns;
        end loop;
        wait;
    end process;
End architecture;

test.vcd
$date
  Thu Dec  5 17:24:10 2019
$end
$version
  GHDL v0
$end
$timescale
  1 fs
$end
$scope module standard $end
$upscope $end
$scope module textio $end
$upscope $end
$scope module std_logic_1164 $end
$upscope $end
$scope module numeric_std $end
$upscope $end
$scope module std_logic_arith $end
$upscope $end
$scope module bus_mux_pkg $end
$upscope $end
$scope module test $end
$var reg 32 ! op_0[31:0] $end
$var reg 32 " op_1[31:0] $end
$var reg 32 # sum[31:0] $end
$var reg 1 $ c $end
$scope module inst_add $end
$var reg 32 % op_0[31:0] $end
$var reg 32 & op_1[31:0] $end
$var reg 32 ' sum[31:0] $end
$var reg 1 ( c $end
$var reg 32 ) carry[31:0] $end
$scope module gen_add(1) $end
$upscope $end
$scope module gen_add(2) $end
$upscope $end
$scope module gen_add(3) $end
$upscope $end
$scope module gen_add(4) $end
$upscope $end
$scope module gen_add(5) $end
$upscope $end
$scope module gen_add(6) $end
$upscope $end
$scope module gen_add(7) $end
$upscope $end
$scope module gen_add(8) $end
$upscope $end
$scope module gen_add(9) $end
$upscope $end
$scope module gen_add(10) $end
$upscope $end
$scope module gen_add(11) $end
$upscope $end
$scope module gen_add(12) $end
$upscope $end
$scope module gen_add(13) $end
$upscope $end
$scope module gen_add(14) $end
$upscope $end
$scope module gen_add(15) $end
$upscope $end
$scope module gen_add(16) $end
$upscope $end
$scope module gen_add(17) $end
$upscope $end
$scope module gen_add(18) $end
$upscope $end
$scope module gen_add(19) $end
$upscope $end
$scope module gen_add(20) $end
$upscope $end
$scope module gen_add(21) $end
$upscope $end
$scope module gen_add(22) $end
$upscope $end
$scope module gen_add(23) $end
$upscope $end
$scope module gen_add(24) $end
$upscope $end
$scope module gen_add(25) $end
$upscope $end
$scope module gen_add(26) $end
$upscope $end
$scope module gen_add(27) $end
$upscope $end
$scope module gen_add(28) $end
$upscope $end
$scope module gen_add(29) $end
$upscope $end
$scope module gen_add(30) $end
$upscope $end
$scope module gen_add(31) $end
$upscope $end
$upscope $end
$upscope $end
$enddefinitions $end
#0
b00000000000000000000000000000001 !
b00000000000000000000000000000000 "
b00000000000000000000000000000001 #
0$
b00000000000000000000000000000001 %
b00000000000000000000000000000000 &
b00000000000000000000000000000001 '
0(
b00000000000000000000000000000000 )
#5000000
b00000000000000000000000000000001 "
b00000000000000000000000000000010 #
b00000000000000000000000000000001 &
b00000000000000000000000000000010 '
b00000000000000000000000000000001 )
#10000000
b00000000000000000000000000000011 "
b00000000000000000000000000000100 #
b00000000000000000000000000000011 &
b00000000000000000000000000000100 '
b00000000000000000000000000000011 )
#15000000
b00000000000000000000000000000111 "
b00000000000000000000000000001000 #
b00000000000000000000000000000111 &
b00000000000000000000000000001000 '
b00000000000000000000000000000111 )
#20000000
b00000000000000000000000000001111 "
b00000000000000000000000000010000 #
b00000000000000000000000000001111 &
b00000000000000000000000000010000 '
b00000000000000000000000000001111 )
#25000000
b00000000000000000000000000011111 "
b00000000000000000000000000100000 #
b00000000000000000000000000011111 &
b00000000000000000000000000100000 '
b00000000000000000000000000011111 )
#30000000
b00000000000000000000000000111111 "
b00000000000000000000000001000000 #
b00000000000000000000000000111111 &
b00000000000000000000000001000000 '
b00000000000000000000000000111111 )
#35000000
b00000000000000000000000001111111 "
b00000000000000000000000010000000 #
b00000000000000000000000001111111 &
b00000000000000000000000010000000 '
b00000000000000000000000001111111 )
#40000000
b00000000000000000000000011111111 "
b00000000000000000000000100000000 #
b00000000000000000000000011111111 &
b00000000000000000000000100000000 '
b00000000000000000000000011111111 )
#45000000
b00000000000000000000000111111111 "
b00000000000000000000001000000000 #
b00000000000000000000000111111111 &
b00000000000000000000001000000000 '
b00000000000000000000000111111111 )
#50000000
b00000000000000000000001111111111 "
b00000000000000000000010000000000 #
b00000000000000000000001111111111 &
b00000000000000000000010000000000 '
b00000000000000000000001111111111 )
#55000000
b00000000000000000000011111111111 "
b00000000000000000000100000000000 #
b00000000000000000000011111111111 &
b00000000000000000000100000000000 '
b00000000000000000000011111111111 )
#60000000
b00000000000000000000111111111111 "
b00000000000000000001000000000000 #
b00000000000000000000111111111111 &
b00000000000000000001000000000000 '
b00000000000000000000111111111111 )
#65000000
b00000000000000000001111111111111 "
b00000000000000000010000000000000 #
b00000000000000000001111111111111 &
b00000000000000000010000000000000 '
b00000000000000000001111111111111 )
#70000000
b00000000000000000011111111111111 "
b00000000000000000100000000000000 #
b00000000000000000011111111111111 &
b00000000000000000100000000000000 '
b00000000000000000011111111111111 )
#75000000
b00000000000000000111111111111111 "
b00000000000000001000000000000000 #
b00000000000000000111111111111111 &
b00000000000000001000000000000000 '
b00000000000000000111111111111111 )
#80000000
b00000000000000001111111111111111 "
b00000000000000010000000000000000 #
b00000000000000001111111111111111 &
b00000000000000010000000000000000 '
b00000000000000001111111111111111 )
#85000000
b00000000000000011111111111111111 "
b00000000000000100000000000000000 #
b00000000000000011111111111111111 &
b00000000000000100000000000000000 '
b00000000000000011111111111111111 )
#90000000
b00000000000000111111111111111111 "
b00000000000001000000000000000000 #
b00000000000000111111111111111111 &
b00000000000001000000000000000000 '
b00000000000000111111111111111111 )
#95000000
b00000000000001111111111111111111 "
b00000000000010000000000000000000 #
b00000000000001111111111111111111 &
b00000000000010000000000000000000 '
b00000000000001111111111111111111 )
#100000000
b00000000000011111111111111111111 "
b00000000000100000000000000000000 #
b00000000000011111111111111111111 &
b00000000000100000000000000000000 '
b00000000000011111111111111111111 )
#105000000
b00000000000111111111111111111111 "
b00000000001000000000000000000000 #
b00000000000111111111111111111111 &
b00000000001000000000000000000000 '
b00000000000111111111111111111111 )
#110000000
b00000000001111111111111111111111 "
b00000000010000000000000000000000 #
b00000000001111111111111111111111 &
b00000000010000000000000000000000 '
b00000000001111111111111111111111 )
#115000000
b00000000011111111111111111111111 "
b00000000100000000000000000000000 #
b00000000011111111111111111111111 &
b00000000100000000000000000000000 '
b00000000011111111111111111111111 )
#120000000
b00000000111111111111111111111111 "
b00000001000000000000000000000000 #
b00000000111111111111111111111111 &
b00000001000000000000000000000000 '
b00000000111111111111111111111111 )
#125000000
b00000001111111111111111111111111 "
b00000010000000000000000000000000 #
b00000001111111111111111111111111 &
b00000010000000000000000000000000 '
b00000001111111111111111111111111 )
#130000000
b00000011111111111111111111111111 "
b00000100000000000000000000000000 #
b00000011111111111111111111111111 &
b00000100000000000000000000000000 '
b00000011111111111111111111111111 )
#135000000
b00000111111111111111111111111111 "
b00001000000000000000000000000000 #
b00000111111111111111111111111111 &
b00001000000000000000000000000000 '
b00000111111111111111111111111111 )
#140000000
b00001111111111111111111111111111 "
b00010000000000000000000000000000 #
b00001111111111111111111111111111 &
b00010000000000000000000000000000 '
b00001111111111111111111111111111 )
#145000000
b00011111111111111111111111111111 "
b00100000000000000000000000000000 #
b00011111111111111111111111111111 &
b00100000000000000000000000000000 '
b00011111111111111111111111111111 )
#150000000
b00111111111111111111111111111111 "
b01000000000000000000000000000000 #
b00111111111111111111111111111111 &
b01000000000000000000000000000000 '
b00111111111111111111111111111111 )
#155000000
b01111111111111111111111111111111 "
b10000000000000000000000000000000 #
b01111111111111111111111111111111 &
b10000000000000000000000000000000 '
b01111111111111111111111111111111 )
#160000000
b11111111111111111111111111111111 "
b00000000000000000000000000000000 #
1$
b11111111111111111111111111111111 &
b00000000000000000000000000000000 '
1(
b11111111111111111111111111111111 )
