reg_para.vhd
LIBRARY IEEE;
USE IEEE.STD_LOGIC_1164.ALL;
USE IEEE.NUMERIC_STD.ALL;

Entity parallel_register is
    Generic
    (
        register_size : Integer := 32
    );
    Port
    (
        wr : In Std_logic;
        data_in : In Std_logic_vector(register_size-1 downto 0);
        data_out : Out Std_logic_vector(register_size-1 downto 0)
    );
End entity parallel_register;

Architecture comp_reg_para of parallel_register is
begin
    process(wr)
    begin
        if rising_edge(wr) then
            data_out <= data_in;
        end if;
    end process;
End Architecture comp_reg_para;

mux.vhd
LIBRARY IEEE;
USE IEEE.STD_LOGIC_1164.ALL;
USE IEEE.NUMERIC_STD.ALL;

Package bus_mux_pkg Is
    Type bus_mux_array is array(natural range<>) of std_logic_vector;
End Package bus_mux_pkg;

LIBRARY IEEE;
USE IEEE.STD_LOGIC_1164.ALL;
USE IEEE.NUMERIC_STD.ALL;
library work;
use work.bus_mux_pkg.all;

Entity multiplexor Is 
    generic
    (
        mux_size : Integer := 2;
        mux_width : Integer := 32
    );
    Port
    (
        input : IN bus_mux_array((2**mux_size)-1 downto 0)(mux_width-1 downto 0);
        sel_input : IN std_logic_vector(mux_size-1 downto 0);
        output : OUT std_logic_vector(mux_width-1 downto 0)
    );
End Entity multiplexor;

ARCHITECTURE fdd_mux OF multiplexor IS
    Begin
        output <= input(to_integer(unsigned(sel_input)));
--         GEN_MUX:
--         for i IN size-1 DOWNTO 0 GENERATE
--             output(i) <= input(sel, i);
--         END GENERATE GEN_MUX;
End ARCHITECTURE fdd_mux;

CombinationalTools/b_shifter.vhd
LIBRARY IEEE;
USE IEEE.STD_LOGIC_1164.ALL;
USE IEEE.NUMERIC_STD.ALL;
LIBRARY CombinationalTools;
USE CombinationalTools.bus_mux_pkg.ALL;


ENTITY barrel_shifter IS
	GENERIC 
	(
		shift_size : INTEGER := 5;
		shifter_width : INTEGER := 32
	);
	PORT
	(
		input : IN STD_LOGIC_VECTOR(31 DOWNTO 0);
		shift_amount : IN STD_LOGIC_VECTOR(shift_size-1 DOWNTO 0);
		LeftRight : IN STD_LOGIC;
		LogicArith : IN STD_LOGIC;
		ShiftRotate : IN STD_LOGIC;
		output : OUT STD_LOGIC_VECTOR(31 DOWNTO 0)
	);
END ENTITY barrel_shifter;

architecture fdd_b_shifter of barrel_shifter is
    subtype Sel is STD_LOGIC_VECTOR(2 downto 0);
begin
    with Sel'(LeftRight & LogicArith & ShiftRotate) select
        output <= input sll to_integer(unsigned(shift_amount)) when "000",
            input rol to_integer(unsigned(shift_amount)) when "001",
            to_stdlogicvector(to_bitvector(input) sla to_integer(signed(shift_amount))) when "010",
            input rol to_integer(unsigned(shift_amount)) when "011",
            input srl to_integer(unsigned(shift_amount)) when "100",
            input ror to_integer(unsigned(shift_amount)) when "101",
            to_stdlogicvector(to_bitvector(input) sra to_integer(signed(shift_amount))) when "110",
            input ror to_integer(unsigned(shift_amount)) when "111",
            input when others;
end architecture fdd_b_shifter;

alu.vhd
LIBRARY IEEE;
USE IEEE.STD_LOGIC_1164.ALL;
USE IEEE.NUMERIC_STD.ALL;

LIBRARY CombinationalTools;
USE CombinationalTools.bus_mux_pkg.ALL;
LIBRARY SequentialTools;
USE SequentialTools.ALL;


ENTITY ALU IS
	PORT
	(
		A : IN STD_LOGIC_VECTOR(31 DOWNTO 0);
		B : IN STD_LOGIC_VECTOR(31 DOWNTO 0);
		sel : IN STD_LOGIC_VECTOR(3 DOWNTO 0);
		Enable_V : IN STD_LOGIC;
		ValDec : IN STD_LOGIC_VECTOR(4 DOWNTO 0);
		Slt : IN STD_LOGIC;
		CLK : IN STD_LOGIC;
		Res : OUT STD_LOGIC_VECTOR(31 DOWNTO 0);
		N : OUT STD_LOGIC;
		Z : OUT STD_LOGIC;
		C : OUT STD_LOGIC;
		V : OUT STD_LOGIC
	);
END ENTITY ALU;

architecture struct_alu of ALU Is
    Component multiplexor Is
    generic
    (
        mux_size : Integer := 3;
        mux_width : Integer := 32
    );
    Port
    (
        input : IN bus_mux_array((2**mux_size)-1 downto 0)(mux_width-1 downto 0);
        sel_input : IN std_logic_vector(mux_size-1 downto 0);
        output : OUT std_logic_vector(mux_width-1 downto 0)
    );
    End Component multiplexor;
    Component barrel_shifter Is
    generic
    (
        shift_size : INTEGER := 5;
        shifter_width : INTEGER := 32
    );
    Port
    (
        input : IN STD_LOGIC_VECTOR(31 DOWNTO 0);
        shift_amount : IN STD_LOGIC_VECTOR(shift_size-1 DOWNTO 0);
        LeftRight : IN STD_LOGIC;
        LogicArith : IN STD_LOGIC;
        ShiftRotate : IN STD_LOGIC;
        output : OUT STD_LOGIC_VECTOR(31 DOWNTO 0)
    );
    END Component barrel_shifter;
    Component parallel_register is
    Generic
    (
        register_size : Integer := 1
    );
    Port
    (
        wr : In Std_logic;
        data_in : In Std_logic_vector(register_size-1 downto 0);
        data_out : Out Std_logic_vector(register_size-1 downto 0)
    );
    End Component parallel_register;
    Signal S_And : STD_LOGIC_VECTOR(31 DOWNTO 0); --Ces signaux font le lien entre les opération logique et le mux
    Signal S_Or : STD_LOGIC_VECTOR(31 DOWNTO 0); --
    Signal S_Nor : STD_LOGIC_VECTOR(31 DOWNTO 0); --
    Signal S_Xor : STD_LOGIC_VECTOR(31 DOWNTO 0); --
    Signal S_LR : Std_logic;

    Signal S_BS : STD_LOGIC_VECTOR(31 DOWNTO 0); -- fait le lien entre la sortie du barrel shifter et le mux
    Signal S_out_mux : std_logic_vector(31 downto 0); -- recupère la sortie du mux pour le brancher ensuite au res et a la bascule D de Z
    Signal S_out_adder : std_logic_vector(31 downto 0); -- signal en sortie de l'additionneur

    --Signaux utilse pour l'add/sub
    Signal flow : Std_logic;
    Signal overflow : Std_logic;
    Signal carry : Std_logic;
    Signal locala, localb, localsum : signed(32 downto 0);
    Signal sumout : std_logic_vector(32 downto 0);

    --bit du résultat pour les opération positionnement si inférieur
    Signal res0 : Std_logic;
    
    Signal tmp : Std_logic_vector(30 downto 0) := (others => '0');
    Signal res0_vec : Std_logic_vector(31 downto 0);
    Signal ZTmp : Std_logic;
    
begin
    S_And <= A and B;
    S_Or <= A or B;
    S_Nor <= A nor B;
    S_Xor <= A xor B;
    S_LR <= not sel(0);

    -- add/subb
    locala <= resize(signed(A), 33);
    localb <= resize(signed(B), 33);
    localsum <= locala + localb when sel(3) = '0' else locala - localb;
    flow <= '1' when localsum(31) /= localsum(32) else '0';
    carry <= '1' when localsum(32) /= sel(3) else '0';
    sumout <= std_logic_vector(localsum);
    S_out_adder <= sumout(32) & sumout(30 downto 0);

    --Logique pour déterminer le bit du résultat res0 pour les opérations positionnement si inférieur.
    res0 <= (Enable_V and (S_out_adder(31) xor overflow)) or ((not Enable_V) and carry);
    res0_vec <= tmp & res0;
    
    bs_inst : entity CombinationalTools.barrel_shifter
        port map(input => B,
            shift_amount => ValDec,
            LeftRight => S_LR,
            LogicArith => '0',
            ShiftRotate => '0',
            output => S_BS);

    mux_inst : entity CombinationalTools.multiplexor
        generic map (  mux_size => 3, mux_width => 32)
        port map( input(0) => S_And,
        input(1) => S_Or,
        input(2) => S_out_adder,
        input(3) => res0_vec,
        input(4) => S_Nor,
        input(5) => S_Xor,
        input(6) => S_BS,
        input(7) => S_BS,
        output => S_out_mux,
        sel_input => sel(2 downto 0));

    res <= S_out_mux;

    --Bascule D pour la sortie C
    inst_reg0 : entity SequentialTools.parallel_register
      port map(wr => CLK,
      data_in(0) => carry,
      data_out(0) => C);

    overflow <= flow and (not Slt) and Enable_V;
    --Bascule D pour la sortie V
    inst_reg1 : entity SequentialTools.parallel_register
      port map(wr => CLK,
      data_in(0) => overflow,
      data_out(0) => V);

    --Bascule D pour la sortie N
    inst_reg2 : entity SequentialTools.parallel_register
      port map(wr => CLK,
      data_in(0) => S_out_adder(31),
      data_out(0) => N);
    
    ZTmp <= '1' when unsigned(S_out_mux) = 0;
    --Bascule D pour la sortie Z
    inst_reg3 : entity SequentialTools.parallel_register
      port map(wr => CLK,
      data_in(0) => ZTmp,
      data_out(0) => Z);
End architecture struct_alu;

testbench_alu.vhd
LIBRARY IEEE;
USE IEEE.STD_LOGIC_1164.ALL;
USE IEEE.NUMERIC_STD.ALL;
use ieee.std_logic_arith.all;
LIBRARY CombinationalTools;
USE CombinationalTools.bus_mux_pkg.ALL;

ENTITY test IS
END ENTITY;

ARCHITECTURE arc OF test IS
    Signal A : STD_LOGIC_VECTOR(31 DOWNTO 0) := (others => '0');
    Signal B : STD_LOGIC_VECTOR(31 DOWNTO 0) := (others => '0');
    Signal sel : STD_LOGIC_VECTOR(3 DOWNTO 0) := (others => '0');
    Signal Enable_V : STD_LOGIC := '0';
    Signal ValDec : STD_LOGIC_VECTOR(4 DOWNTO 0) := (others => '0');
    Signal Slt : STD_LOGIC := '0';
    Signal CLK : STD_LOGIC := '0';
    Signal Res : STD_LOGIC_VECTOR(31 DOWNTO 0) := (others => '0');
    Signal N : STD_LOGIC := '0';
    Signal Z : STD_LOGIC := '0';
    Signal C : STD_LOGIC := '0';
    Signal V : STD_LOGIC := '0';
BEGIN
    --test du circuit decoder
    inst_alu : ENTITY work.ALU(struct_alu) PORT MAP (A,B,sel,Enable_V,ValDec,Slt,CLK,Res,N,Z,C,V);
    PROCESS 
    BEGIN
        A <= conv_std_logic_vector(8,A'length);
        B <= conv_std_logic_vector(2,A'length);
        ValDec <= conv_std_logic_vector(1,ValDec'length);
        FOR I IN 0 to 7 LOOP
            sel <= conv_std_logic_vector(I,sel'length);
            WAIT FOR 5 ns;
        END LOOP;
        WAIT; --pour terminer le test bench
    END PROCESS;
END ARCHITECTURE;

test.vcd
$date
  Wed Dec  4 08:59:41 2019
$end
$version
  GHDL v0
$end
$timescale
  1 fs
$end
$scope module standard $end
$upscope $end
$scope module textio $end
$upscope $end
$scope module std_logic_1164 $end
$upscope $end
$scope module numeric_std $end
$upscope $end
$scope module std_logic_arith $end
$upscope $end
$scope module bus_mux_pkg $end
$upscope $end
$scope module test $end
$var reg 32 ! a[31:0] $end
$var reg 32 " b[31:0] $end
$var reg 4 # sel[3:0] $end
$var reg 1 $ enable_v $end
$var reg 5 % valdec[4:0] $end
$var reg 1 & slt $end
$var reg 1 ' clk $end
$var reg 32 ( res[31:0] $end
$var reg 1 ) n $end
$var reg 1 * z $end
$var reg 1 + c $end
$var reg 1 , v $end
$scope module inst_alu $end
$var reg 32 - a[31:0] $end
$var reg 32 . b[31:0] $end
$var reg 4 / sel[3:0] $end
$var reg 1 0 enable_v $end
$var reg 5 1 valdec[4:0] $end
$var reg 1 2 slt $end
$var reg 1 3 clk $end
$var reg 32 4 res[31:0] $end
$var reg 1 5 n $end
$var reg 1 6 z $end
$var reg 1 7 c $end
$var reg 1 8 v $end
$var reg 32 9 s_and[31:0] $end
$var reg 32 : s_or[31:0] $end
$var reg 32 ; s_nor[31:0] $end
$var reg 32 < s_xor[31:0] $end
$var reg 1 = s_lr $end
$var reg 32 > s_bs[31:0] $end
$var reg 32 ? s_out_mux[31:0] $end
$var reg 32 @ s_out_adder[31:0] $end
$var reg 1 A flow $end
$var reg 1 B overflow $end
$var reg 1 C carry $end
$var reg 33 D locala[32:0] $end
$var reg 33 E localb[32:0] $end
$var reg 33 F localsum[32:0] $end
$var reg 33 G sumout[32:0] $end
$var reg 1 H res0 $end
$var reg 31 I tmp[30:0] $end
$var reg 32 J res0_vec[31:0] $end
$var reg 1 K ztmp $end
$scope module bs_inst $end
$var reg 32 L input[31:0] $end
$var reg 5 M shift_amount[4:0] $end
$var reg 1 N leftright $end
$var reg 1 O logicarith $end
$var reg 1 P shiftrotate $end
$var reg 32 Q output[31:0] $end
$upscope $end
$scope module mux_inst $end
$comment input is not handled $end
$var reg 3 R sel_input[2:0] $end
$var reg 32 S output[31:0] $end
$upscope $end
$scope module inst_reg0 $end
$var reg 1 T wr $end
$var reg 32 U data_in[31:0] $end
$var reg 32 V data_out[31:0] $end
$upscope $end
$scope module inst_reg1 $end
$var reg 1 W wr $end
$var reg 32 X data_in[31:0] $end
$var reg 32 Y data_out[31:0] $end
$upscope $end
$scope module inst_reg2 $end
$var reg 1 Z wr $end
$var reg 32 [ data_in[31:0] $end
$var reg 32 \ data_out[31:0] $end
$upscope $end
$scope module inst_reg3 $end
$var reg 1 ] wr $end
$var reg 32 ^ data_in[31:0] $end
$var reg 32 _ data_out[31:0] $end
$upscope $end
$upscope $end
$upscope $end
$enddefinitions $end
#0
b00000000000000000000000000001000 !
b00000000000000000000000000000010 "
b0000 #
0$
b00001 %
0&
0'
b00000000000000000000000000000000 (
U)
U*
U+
U,
b00000000000000000000000000001000 -
b00000000000000000000000000000010 .
b0000 /
00
b00001 1
02
03
b00000000000000000000000000000000 4
U5
U6
U7
U8
b00000000000000000000000000000000 9
b00000000000000000000000000001010 :
b11111111111111111111111111110101 ;
b00000000000000000000000000001010 <
1=
b00000000000000000000000000000001 >
b00000000000000000000000000000000 ?
b00000000000000000000000000001010 @
0A
0B
0C
b000000000000000000000000000001000 D
b000000000000000000000000000000010 E
b000000000000000000000000000001010 F
b000000000000000000000000000001010 G
0H
b0000000000000000000000000000000 I
b00000000000000000000000000000000 J
1K
b00000000000000000000000000000010 L
b00001 M
1N
0O
0P
b00000000000000000000000000000001 Q
b000 R
b00000000000000000000000000000000 S
0T
bUUUUUUUUUUUUUUUUUUUUUUUUUUUUUUU0 U
bUUUUUUUUUUUUUUUUUUUUUUUUUUUUUUUU V
0W
bUUUUUUUUUUUUUUUUUUUUUUUUUUUUUUU0 X
bUUUUUUUUUUUUUUUUUUUUUUUUUUUUUUUU Y
0Z
bUUUUUUUUUUUUUUUUUUUUUUUUUUUUUUU0 [
bUUUUUUUUUUUUUUUUUUUUUUUUUUUUUUUU \
0]
bUUUUUUUUUUUUUUUUUUUUUUUUUUUUUUU1 ^
bUUUUUUUUUUUUUUUUUUUUUUUUUUUUUUUU _
#5000000
b0001 #
b00000000000000000000000000001010 (
b0001 /
b00000000000000000000000000001010 4
0=
b00000000000000000000000000000100 >
b00000000000000000000000000001010 ?
0N
b00000000000000000000000000000100 Q
b001 R
b00000000000000000000000000001010 S
#10000000
b0010 #
b0010 /
1=
b00000000000000000000000000000001 >
1N
b00000000000000000000000000000001 Q
b010 R
#15000000
b0011 #
b00000000000000000000000000000000 (
b0011 /
b00000000000000000000000000000000 4
0=
b00000000000000000000000000000100 >
b00000000000000000000000000000000 ?
0N
b00000000000000000000000000000100 Q
b011 R
b00000000000000000000000000000000 S
#20000000
b0100 #
b11111111111111111111111111110101 (
b0100 /
b11111111111111111111111111110101 4
1=
b00000000000000000000000000000001 >
b11111111111111111111111111110101 ?
1N
b00000000000000000000000000000001 Q
b100 R
b11111111111111111111111111110101 S
#25000000
b0101 #
b00000000000000000000000000001010 (
b0101 /
b00000000000000000000000000001010 4
0=
b00000000000000000000000000000100 >
b00000000000000000000000000001010 ?
0N
b00000000000000000000000000000100 Q
b101 R
b00000000000000000000000000001010 S
#30000000
b0110 #
b00000000000000000000000000000001 (
b0110 /
b00000000000000000000000000000001 4
1=
b00000000000000000000000000000001 >
b00000000000000000000000000000001 ?
1N
b00000000000000000000000000000001 Q
b110 R
b00000000000000000000000000000001 S
#35000000
b0111 #
b00000000000000000000000000000100 (
b0111 /
b00000000000000000000000000000100 4
0=
b00000000000000000000000000000100 >
b00000000000000000000000000000100 ?
0N
b00000000000000000000000000000100 Q
b111 R
b00000000000000000000000000000100 S
