reg_para.vhd
LIBRARY IEEE;
USE IEEE.STD_LOGIC_1164.ALL;
USE IEEE.NUMERIC_STD.ALL;

Entity parallel_register is
    Generic
    (
        register_size : Integer := 32
    );
    Port
    (
        wr : In Std_logic;
        data_in : In Std_logic_vector(register_size-1 downto 0);
        data_out : Out Std_logic_vector(register_size-1 downto 0)
    );
End entity parallel_register;

Architecture comp_reg_para of parallel_register is
begin
    process(wr)
    begin
        if rising_edge(wr) then
            data_out <= data_in;
        end if;
    end process;
End Architecture comp_reg_para;

mux.vhd
LIBRARY IEEE;
USE IEEE.STD_LOGIC_1164.ALL;
USE IEEE.NUMERIC_STD.ALL;

Package bus_mux_pkg Is
    Type bus_mux_array is array(natural range<>) of std_logic_vector;
End Package bus_mux_pkg;

LIBRARY IEEE;
USE IEEE.STD_LOGIC_1164.ALL;
USE IEEE.NUMERIC_STD.ALL;
library work;
use work.bus_mux_pkg.all;

Entity multiplexor Is 
    generic
    (
        mux_size : Integer := 2;
        mux_width : Integer := 32
    );
    Port
    (
        input : IN bus_mux_array((2**mux_size)-1 downto 0)(mux_width-1 downto 0);
        sel_input : IN std_logic_vector(mux_size-1 downto 0);
        output : OUT std_logic_vector(mux_width-1 downto 0)
    );
End Entity multiplexor;

ARCHITECTURE fdd_mux OF multiplexor IS
    Begin
        output <= input(to_integer(unsigned(sel_input)));
--         GEN_MUX:
--         for i IN size-1 DOWNTO 0 GENERATE
--             output(i) <= input(sel, i);
--         END GENERATE GEN_MUX;
End ARCHITECTURE fdd_mux;

CombinationalTools/b_shifter.vhd
LIBRARY IEEE;
USE IEEE.STD_LOGIC_1164.ALL;
USE IEEE.NUMERIC_STD.ALL;
LIBRARY CombinationalTools;
USE CombinationalTools.bus_mux_pkg.ALL;


ENTITY barrel_shifter IS
	GENERIC 
	(
		shift_size : INTEGER := 5;
		shifter_width : INTEGER := 32
	);
	PORT
	(
		input : IN STD_LOGIC_VECTOR(31 DOWNTO 0);
		shift_amount : IN STD_LOGIC_VECTOR(shift_size-1 DOWNTO 0);
		LeftRight : IN STD_LOGIC;
		LogicArith : IN STD_LOGIC;
		ShiftRotate : IN STD_LOGIC;
		output : OUT STD_LOGIC_VECTOR(31 DOWNTO 0)
	);
END ENTITY barrel_shifter;

architecture fdd_b_shifter of barrel_shifter is
    subtype Sel is STD_LOGIC_VECTOR(2 downto 0);
begin
    with Sel'(LeftRight & LogicArith & ShiftRotate) select
        output <= input sll to_integer(unsigned(shift_amount)) when "000",
            input rol to_integer(unsigned(shift_amount)) when "001",
            to_stdlogicvector(to_bitvector(input) sla to_integer(signed(shift_amount))) when "010",
            input rol to_integer(unsigned(shift_amount)) when "011",
            input srl to_integer(unsigned(shift_amount)) when "100",
            input ror to_integer(unsigned(shift_amount)) when "101",
            to_stdlogicvector(to_bitvector(input) sra to_integer(signed(shift_amount))) when "110",
            input ror to_integer(unsigned(shift_amount)) when "111",
            input when others;
end architecture fdd_b_shifter;

alu.vhd
LIBRARY IEEE;
USE IEEE.STD_LOGIC_1164.ALL;
USE IEEE.NUMERIC_STD.ALL;

LIBRARY CombinationalTools;
USE CombinationalTools.bus_mux_pkg.ALL;
LIBRARY SequentialTools;
USE SequentialTools.ALL;


ENTITY ALU IS
	PORT
	(
		A : IN STD_LOGIC_VECTOR(31 DOWNTO 0);
		B : IN STD_LOGIC_VECTOR(31 DOWNTO 0);
		sel : IN STD_LOGIC_VECTOR(3 DOWNTO 0);
		Enable_V : IN STD_LOGIC;
		ValDec : IN STD_LOGIC_VECTOR(4 DOWNTO 0);
		Slt : IN STD_LOGIC;
		CLK : IN STD_LOGIC;
		Res : OUT STD_LOGIC_VECTOR(31 DOWNTO 0);
		N : OUT STD_LOGIC;
		Z : OUT STD_LOGIC;
		C : OUT STD_LOGIC;
		V : OUT STD_LOGIC
	);
END ENTITY ALU;

architecture struct_alu of ALU Is
    Component multiplexor Is
    generic
    (
        mux_size : Integer := 3;
        mux_width : Integer := 32
    );
    Port
    (
        input : IN bus_mux_array((2**mux_size)-1 downto 0)(mux_width-1 downto 0);
        sel_input : IN std_logic_vector(mux_size-1 downto 0);
        output : OUT std_logic_vector(mux_width-1 downto 0)
    );
    End Component multiplexor;
    Component barrel_shifter Is
    generic
    (
        shift_size : INTEGER := 5;
        shifter_width : INTEGER := 32
    );
    Port
    (
        input : IN STD_LOGIC_VECTOR(31 DOWNTO 0);
        shift_amount : IN STD_LOGIC_VECTOR(shift_size-1 DOWNTO 0);
        LeftRight : IN STD_LOGIC;
        LogicArith : IN STD_LOGIC;
        ShiftRotate : IN STD_LOGIC;
        output : OUT STD_LOGIC_VECTOR(31 DOWNTO 0)
    );
    END Component barrel_shifter;
    Component parallel_register is
    Generic
    (
        register_size : Integer := 1
    );
    Port
    (
        wr : In Std_logic;
        data_in : In Std_logic_vector(register_size-1 downto 0);
        data_out : Out Std_logic_vector(register_size-1 downto 0)
    );
    End Component parallel_register;
    Signal S_And : STD_LOGIC_VECTOR(31 DOWNTO 0); --Ces signaux font le lien entre les opération logique et le mux
    Signal S_Or : STD_LOGIC_VECTOR(31 DOWNTO 0); --
    Signal S_Nor : STD_LOGIC_VECTOR(31 DOWNTO 0); --
    Signal S_Xor : STD_LOGIC_VECTOR(31 DOWNTO 0); --
    Signal S_LR : Std_logic;

    Signal S_BS : STD_LOGIC_VECTOR(31 DOWNTO 0); -- fait le lien entre la sortie du barrel shifter et le mux
    Signal S_out_mux : std_logic_vector(31 downto 0); -- recupère la sortie du mux pour le brancher ensuite au res et a la bascule D de Z
    Signal S_out_adder : std_logic_vector(31 downto 0); -- signal en sortie de l'additionneur

    --Signaux utilse pour l'add/sub
    Signal flow : Std_logic;
    Signal overflow : Std_logic;
    Signal carry : Std_logic;
    Signal locala, localb, localsum : signed(32 downto 0);
    Signal sumout : std_logic_vector(32 downto 0);

    --bit du résultat pour les opération positionnement si inférieur
    Signal res0 : Std_logic;
    
    Signal tmp : Std_logic_vector(30 downto 0) := (others => '0');
    Signal res0_vec : Std_logic_vector(31 downto 0);
    Signal ZTmp : Std_logic;
    
begin
    S_And <= A and B;
    S_Or <= A or B;
    S_Nor <= A nor B;
    S_Xor <= A xor B;
    S_LR <= not sel(0);

    -- add/subb
    locala <= resize(signed(A), 33);
    localb <= resize(signed(B), 33);
    localsum <= locala + localb when sel(3) = '0' else locala - localb;
    flow <= '1' when localsum(31) /= localsum(32) else '0';
    carry <= '1' when localsum(32) /= sel(3) else '0';
    sumout <= std_logic_vector(localsum);
    S_out_adder <= sumout(32) & sumout(30 downto 0);

    --Logique pour déterminer le bit du résultat res0 pour les opérations positionnement si inférieur.
    res0 <= (Enable_V and (S_out_adder(31) xor overflow)) or ((not Enable_V) and carry);
    res0_vec <= tmp & res0;
    
    bs_inst : entity CombinationalTools.barrel_shifter
        port map(input => B,
            shift_amount => ValDec,
            LeftRight => S_LR,
            LogicArith => '0',
            ShiftRotate => '0',
            output => S_BS);

    mux_inst : entity CombinationalTools.multiplexor
        generic map (  mux_size => 3, mux_width => 32)
        port map( input(0) => S_And,
        input(1) => S_Or,
        input(2) => S_out_adder,
        input(3) => res0_vec,
        input(4) => S_Nor,
        input(5) => S_Xor,
        input(6) => S_BS,
        input(7) => S_BS,
        output => S_out_mux,
        sel_input => sel(2 downto 0));

    res <= S_out_mux;

    --Bascule D pour la sortie C
    inst_reg0 : entity SequentialTools.parallel_register
        generic map (  register_size => 1)
        port map(wr => CLK,
        data_in(0) => carry,
        data_out(0) => C);

    overflow <= flow and (not Slt) and Enable_V;
    --Bascule D pour la sortie V
    inst_reg1 : entity SequentialTools.parallel_register
        generic map (  register_size => 1)
        port map(wr => CLK,
        data_in(0) => overflow,
        data_out(0) => V);

    --Bascule D pour la sortie N
    inst_reg2 : entity SequentialTools.parallel_register
        generic map (  register_size => 1)
        port map(wr => CLK,
        data_in(0) => S_out_adder(31),
        data_out(0) => N);
    
    ZTmp <= '1' when unsigned(S_out_mux) = 0 else '0';
    --Bascule D pour la sortie Z
    inst_reg3 : entity SequentialTools.parallel_register
        generic map (  register_size => 1)
        port map(wr => CLK,
        data_in(0) => ZTmp,
        data_out(0) => Z);
End architecture struct_alu;

testbench_alu.vhd
LIBRARY IEEE;
USE IEEE.STD_LOGIC_1164.ALL;
USE IEEE.NUMERIC_STD.ALL;
use ieee.std_logic_arith.all;
LIBRARY CombinationalTools;
USE CombinationalTools.bus_mux_pkg.ALL;

ENTITY test IS
END ENTITY;

ARCHITECTURE arc OF test IS
    Signal A : STD_LOGIC_VECTOR(31 DOWNTO 0) := (others => '0');
    Signal B : STD_LOGIC_VECTOR(31 DOWNTO 0) := (others => '0');
    Signal sel : STD_LOGIC_VECTOR(3 DOWNTO 0) := (others => '0');
    Signal Enable_V : STD_LOGIC := '0';
    Signal ValDec : STD_LOGIC_VECTOR(4 DOWNTO 0) := (others => '0');
    Signal Slt : STD_LOGIC := '0';
    Signal CLK : STD_LOGIC := '0';
    Signal Res : STD_LOGIC_VECTOR(31 DOWNTO 0) := (others => '0');
    Signal N : STD_LOGIC := '0';
    Signal Z : STD_LOGIC := '0';
    Signal C : STD_LOGIC := '0';
    Signal V : STD_LOGIC := '0';
BEGIN
    --test du circuit decoder
    inst_alu : ENTITY work.ALU(struct_alu) PORT MAP (A,B,sel,Enable_V,ValDec,Slt,CLK,Res,N,Z,C,V);
    PROCESS 
    BEGIN
        A <= conv_std_logic_vector(8,A'length);
        B <= conv_std_logic_vector(2,B'length);
        Slt <= '0';
        ValDec <= conv_std_logic_vector(1,ValDec'length);
        Enable_V <= '1';
        FOR I IN 0 to 15 LOOP
            sel <= conv_std_logic_vector(I,sel'length);
            WAIT FOR 5 ns;
            CLK <= '1';
            WAIT FOR 5 ns;
            CLK <= '0';
            WAIT FOR 5 ns;
        END LOOP;
        
        --test avec des négatifs
        A <= conv_std_logic_vector(8,A'length);
        B <= conv_std_logic_vector(-9,B'length);
        Slt <= '0';
        ValDec <= conv_std_logic_vector(1,ValDec'length);
        Enable_V <= '1';
        FOR I IN 0 to 15 LOOP
            sel <= conv_std_logic_vector(I,sel'length);
            WAIT FOR 5 ns;
            CLK <= '1';
            WAIT FOR 5 ns;
            CLK <= '0';
            WAIT FOR 5 ns;
        END LOOP;
        WAIT; --pour terminer le test bench
    END PROCESS;
END ARCHITECTURE;

test.vcd
$date
  Wed Dec  4 11:59:46 2019
$end
$version
  GHDL v0
$end
$timescale
  1 fs
$end
$scope module standard $end
$upscope $end
$scope module textio $end
$upscope $end
$scope module std_logic_1164 $end
$upscope $end
$scope module numeric_std $end
$upscope $end
$scope module std_logic_arith $end
$upscope $end
$scope module bus_mux_pkg $end
$upscope $end
$scope module test $end
$var reg 32 ! a[31:0] $end
$var reg 32 " b[31:0] $end
$var reg 4 # sel[3:0] $end
$var reg 1 $ enable_v $end
$var reg 5 % valdec[4:0] $end
$var reg 1 & slt $end
$var reg 1 ' clk $end
$var reg 32 ( res[31:0] $end
$var reg 1 ) n $end
$var reg 1 * z $end
$var reg 1 + c $end
$var reg 1 , v $end
$scope module inst_alu $end
$var reg 32 - a[31:0] $end
$var reg 32 . b[31:0] $end
$var reg 4 / sel[3:0] $end
$var reg 1 0 enable_v $end
$var reg 5 1 valdec[4:0] $end
$var reg 1 2 slt $end
$var reg 1 3 clk $end
$var reg 32 4 res[31:0] $end
$var reg 1 5 n $end
$var reg 1 6 z $end
$var reg 1 7 c $end
$var reg 1 8 v $end
$var reg 32 9 s_and[31:0] $end
$var reg 32 : s_or[31:0] $end
$var reg 32 ; s_nor[31:0] $end
$var reg 32 < s_xor[31:0] $end
$var reg 1 = s_lr $end
$var reg 32 > s_bs[31:0] $end
$var reg 32 ? s_out_mux[31:0] $end
$var reg 32 @ s_out_adder[31:0] $end
$var reg 1 A flow $end
$var reg 1 B overflow $end
$var reg 1 C carry $end
$var reg 33 D locala[32:0] $end
$var reg 33 E localb[32:0] $end
$var reg 33 F localsum[32:0] $end
$var reg 33 G sumout[32:0] $end
$var reg 1 H res0 $end
$var reg 31 I tmp[30:0] $end
$var reg 32 J res0_vec[31:0] $end
$var reg 1 K ztmp $end
$scope module bs_inst $end
$var reg 32 L input[31:0] $end
$var reg 5 M shift_amount[4:0] $end
$var reg 1 N leftright $end
$var reg 1 O logicarith $end
$var reg 1 P shiftrotate $end
$var reg 32 Q output[31:0] $end
$upscope $end
$scope module mux_inst $end
$comment input is not handled $end
$var reg 3 R sel_input[2:0] $end
$var reg 32 S output[31:0] $end
$upscope $end
$scope module inst_reg0 $end
$var reg 1 T wr $end
$var reg 1 U data_in[0:0] $end
$var reg 1 V data_out[0:0] $end
$upscope $end
$scope module inst_reg1 $end
$var reg 1 W wr $end
$var reg 1 X data_in[0:0] $end
$var reg 1 Y data_out[0:0] $end
$upscope $end
$scope module inst_reg2 $end
$var reg 1 Z wr $end
$var reg 1 [ data_in[0:0] $end
$var reg 1 \ data_out[0:0] $end
$upscope $end
$scope module inst_reg3 $end
$var reg 1 ] wr $end
$var reg 1 ^ data_in[0:0] $end
$var reg 1 _ data_out[0:0] $end
$upscope $end
$upscope $end
$upscope $end
$enddefinitions $end
#0
b00000000000000000000000000001000 !
b00000000000000000000000000000010 "
b0000 #
1$
b00001 %
0&
0'
b00000000000000000000000000000000 (
U)
U*
U+
U,
b00000000000000000000000000001000 -
b00000000000000000000000000000010 .
b0000 /
10
b00001 1
02
03
b00000000000000000000000000000000 4
U5
U6
U7
U8
b00000000000000000000000000000000 9
b00000000000000000000000000001010 :
b11111111111111111111111111110101 ;
b00000000000000000000000000001010 <
1=
b00000000000000000000000000000001 >
b00000000000000000000000000000000 ?
b00000000000000000000000000001010 @
0A
0B
0C
b000000000000000000000000000001000 D
b000000000000000000000000000000010 E
b000000000000000000000000000001010 F
b000000000000000000000000000001010 G
0H
b0000000000000000000000000000000 I
b00000000000000000000000000000000 J
1K
b00000000000000000000000000000010 L
b00001 M
1N
0O
0P
b00000000000000000000000000000001 Q
b000 R
b00000000000000000000000000000000 S
0T
b0 U
bU V
0W
b0 X
bU Y
0Z
b0 [
bU \
0]
b1 ^
bU _
#5000000
1'
0)
1*
0+
0,
13
05
16
07
08
1T
b0 V
1W
b0 Y
1Z
b0 \
1]
b1 _
#10000000
0'
03
0T
0W
0Z
0]
#15000000
b0001 #
b00000000000000000000000000001010 (
b0001 /
b00000000000000000000000000001010 4
0=
b00000000000000000000000000000100 >
b00000000000000000000000000001010 ?
0K
0N
b00000000000000000000000000000100 Q
b001 R
b00000000000000000000000000001010 S
b0 ^
#20000000
1'
0*
13
06
1T
1W
1Z
1]
b0 _
#25000000
0'
03
0T
0W
0Z
0]
#30000000
b0010 #
b0010 /
1=
b00000000000000000000000000000001 >
1N
b00000000000000000000000000000001 Q
b010 R
#35000000
1'
13
1T
1W
1Z
1]
#40000000
0'
03
0T
0W
0Z
0]
#45000000
b0011 #
b00000000000000000000000000000000 (
b0011 /
b00000000000000000000000000000000 4
0=
b00000000000000000000000000000100 >
b00000000000000000000000000000000 ?
1K
0N
b00000000000000000000000000000100 Q
b011 R
b00000000000000000000000000000000 S
b1 ^
#50000000
1'
1*
13
16
1T
1W
1Z
1]
b1 _
#55000000
0'
03
0T
0W
0Z
0]
#60000000
b0100 #
b11111111111111111111111111110101 (
b0100 /
b11111111111111111111111111110101 4
1=
b00000000000000000000000000000001 >
b11111111111111111111111111110101 ?
0K
1N
b00000000000000000000000000000001 Q
b100 R
b11111111111111111111111111110101 S
b0 ^
#65000000
1'
0*
13
06
1T
1W
1Z
1]
b0 _
#70000000
0'
03
0T
0W
0Z
0]
#75000000
b0101 #
b00000000000000000000000000001010 (
b0101 /
b00000000000000000000000000001010 4
0=
b00000000000000000000000000000100 >
b00000000000000000000000000001010 ?
0N
b00000000000000000000000000000100 Q
b101 R
b00000000000000000000000000001010 S
#80000000
1'
13
1T
1W
1Z
1]
#85000000
0'
03
0T
0W
0Z
0]
#90000000
b0110 #
b00000000000000000000000000000001 (
b0110 /
b00000000000000000000000000000001 4
1=
b00000000000000000000000000000001 >
b00000000000000000000000000000001 ?
1N
b00000000000000000000000000000001 Q
b110 R
b00000000000000000000000000000001 S
#95000000
1'
13
1T
1W
1Z
1]
#100000000
0'
03
0T
0W
0Z
0]
#105000000
b0111 #
b00000000000000000000000000000100 (
b0111 /
b00000000000000000000000000000100 4
0=
b00000000000000000000000000000100 >
b00000000000000000000000000000100 ?
0N
b00000000000000000000000000000100 Q
b111 R
b00000000000000000000000000000100 S
#110000000
1'
13
1T
1W
1Z
1]
#115000000
0'
03
0T
0W
0Z
0]
#120000000
b1000 #
b00000000000000000000000000000000 (
b1000 /
b00000000000000000000000000000000 4
1=
b00000000000000000000000000000001 >
b00000000000000000000000000000000 ?
b00000000000000000000000000000110 @
1C
b000000000000000000000000000000110 F
b000000000000000000000000000000110 G
1K
1N
b00000000000000000000000000000001 Q
b000 R
b00000000000000000000000000000000 S
b1 U
b1 ^
#125000000
1'
1*
1+
13
16
17
1T
b1 V
1W
1Z
1]
b1 _
#130000000
0'
03
0T
0W
0Z
0]
#135000000
b1001 #
b00000000000000000000000000001010 (
b1001 /
b00000000000000000000000000001010 4
0=
b00000000000000000000000000000100 >
b00000000000000000000000000001010 ?
0K
0N
b00000000000000000000000000000100 Q
b001 R
b00000000000000000000000000001010 S
b0 ^
#140000000
1'
0*
13
06
1T
1W
1Z
1]
b0 _
#145000000
0'
03
0T
0W
0Z
0]
#150000000
b1010 #
b00000000000000000000000000000110 (
b1010 /
b00000000000000000000000000000110 4
1=
b00000000000000000000000000000001 >
b00000000000000000000000000000110 ?
1N
b00000000000000000000000000000001 Q
b010 R
b00000000000000000000000000000110 S
#155000000
1'
13
1T
1W
1Z
1]
#160000000
0'
03
0T
0W
0Z
0]
#165000000
b1011 #
b00000000000000000000000000000000 (
b1011 /
b00000000000000000000000000000000 4
0=
b00000000000000000000000000000100 >
b00000000000000000000000000000000 ?
1K
0N
b00000000000000000000000000000100 Q
b011 R
b00000000000000000000000000000000 S
b1 ^
#170000000
1'
1*
13
16
1T
1W
1Z
1]
b1 _
#175000000
0'
03
0T
0W
0Z
0]
#180000000
b1100 #
b11111111111111111111111111110101 (
b1100 /
b11111111111111111111111111110101 4
1=
b00000000000000000000000000000001 >
b11111111111111111111111111110101 ?
0K
1N
b00000000000000000000000000000001 Q
b100 R
b11111111111111111111111111110101 S
b0 ^
#185000000
1'
0*
13
06
1T
1W
1Z
1]
b0 _
#190000000
0'
03
0T
0W
0Z
0]
#195000000
b1101 #
b00000000000000000000000000001010 (
b1101 /
b00000000000000000000000000001010 4
0=
b00000000000000000000000000000100 >
b00000000000000000000000000001010 ?
0N
b00000000000000000000000000000100 Q
b101 R
b00000000000000000000000000001010 S
#200000000
1'
13
1T
1W
1Z
1]
#205000000
0'
03
0T
0W
0Z
0]
#210000000
b1110 #
b00000000000000000000000000000001 (
b1110 /
b00000000000000000000000000000001 4
1=
b00000000000000000000000000000001 >
b00000000000000000000000000000001 ?
1N
b00000000000000000000000000000001 Q
b110 R
b00000000000000000000000000000001 S
#215000000
1'
13
1T
1W
1Z
1]
#220000000
0'
03
0T
0W
0Z
0]
#225000000
b1111 #
b00000000000000000000000000000100 (
b1111 /
b00000000000000000000000000000100 4
0=
b00000000000000000000000000000100 >
b00000000000000000000000000000100 ?
0N
b00000000000000000000000000000100 Q
b111 R
b00000000000000000000000000000100 S
#230000000
1'
13
1T
1W
1Z
1]
#235000000
0'
03
0T
0W
0Z
0]
#240000000
b11111111111111111111111111110111 "
b0000 #
b00000000000000000000000000000000 (
b11111111111111111111111111110111 .
b0000 /
b00000000000000000000000000000000 4
b11111111111111111111111111111111 :
b00000000000000000000000000000000 ;
b11111111111111111111111111111111 <
1=
b01111111111111111111111111111011 >
b00000000000000000000000000000000 ?
b11111111111111111111111111111111 @
1C
b111111111111111111111111111110111 E
b111111111111111111111111111111111 F
b111111111111111111111111111111111 G
1H
b00000000000000000000000000000001 J
1K
b11111111111111111111111111110111 L
1N
b01111111111111111111111111111011 Q
b000 R
b00000000000000000000000000000000 S
b1 U
b1 [
b1 ^
#245000000
1'
1)
1*
13
15
16
1T
1W
1Z
b1 \
1]
b1 _
#250000000
0'
03
0T
0W
0Z
0]
#255000000
b0001 #
b11111111111111111111111111111111 (
b0001 /
b11111111111111111111111111111111 4
0=
b11111111111111111111111111101110 >
b11111111111111111111111111111111 ?
0K
0N
b11111111111111111111111111101110 Q
b001 R
b11111111111111111111111111111111 S
b0 ^
#260000000
1'
0*
13
06
1T
1W
1Z
1]
b0 _
#265000000
0'
03
0T
0W
0Z
0]
#270000000
b0010 #
b0010 /
1=
b01111111111111111111111111111011 >
1N
b01111111111111111111111111111011 Q
b010 R
#275000000
1'
13
1T
1W
1Z
1]
#280000000
0'
03
0T
0W
0Z
0]
#285000000
b0011 #
b00000000000000000000000000000001 (
b0011 /
b00000000000000000000000000000001 4
0=
b11111111111111111111111111101110 >
b00000000000000000000000000000001 ?
0N
b11111111111111111111111111101110 Q
b011 R
b00000000000000000000000000000001 S
#290000000
1'
13
1T
1W
1Z
1]
#295000000
0'
03
0T
0W
0Z
0]
#300000000
b0100 #
b00000000000000000000000000000000 (
b0100 /
b00000000000000000000000000000000 4
1=
b01111111111111111111111111111011 >
b00000000000000000000000000000000 ?
1K
1N
b01111111111111111111111111111011 Q
b100 R
b00000000000000000000000000000000 S
b1 ^
#305000000
1'
1*
13
16
1T
1W
1Z
1]
b1 _
#310000000
0'
03
0T
0W
0Z
0]
#315000000
b0101 #
b11111111111111111111111111111111 (
b0101 /
b11111111111111111111111111111111 4
0=
b11111111111111111111111111101110 >
b11111111111111111111111111111111 ?
0K
0N
b11111111111111111111111111101110 Q
b101 R
b11111111111111111111111111111111 S
b0 ^
#320000000
1'
0*
13
06
1T
1W
1Z
1]
b0 _
#325000000
0'
03
0T
0W
0Z
0]
#330000000
b0110 #
b01111111111111111111111111111011 (
b0110 /
b01111111111111111111111111111011 4
1=
b01111111111111111111111111111011 >
b01111111111111111111111111111011 ?
1N
b01111111111111111111111111111011 Q
b110 R
b01111111111111111111111111111011 S
#335000000
1'
13
1T
1W
1Z
1]
#340000000
0'
03
0T
0W
0Z
0]
#345000000
b0111 #
b11111111111111111111111111101110 (
b0111 /
b11111111111111111111111111101110 4
0=
b11111111111111111111111111101110 >
b11111111111111111111111111101110 ?
0N
b11111111111111111111111111101110 Q
b111 R
b11111111111111111111111111101110 S
#350000000
1'
13
1T
1W
1Z
1]
#355000000
0'
03
0T
0W
0Z
0]
#360000000
b1000 #
b00000000000000000000000000000000 (
b1000 /
b00000000000000000000000000000000 4
1=
b01111111111111111111111111111011 >
b00000000000000000000000000000000 ?
b00000000000000000000000000010001 @
1C
b000000000000000000000000000010001 F
b000000000000000000000000000010001 G
0H
b00000000000000000000000000000000 J
1K
1N
b01111111111111111111111111111011 Q
b000 R
b00000000000000000000000000000000 S
b1 U
b0 [
b1 ^
#365000000
1'
0)
1*
13
05
16
1T
1W
1Z
b0 \
1]
b1 _
#370000000
0'
03
0T
0W
0Z
0]
#375000000
b1001 #
b11111111111111111111111111111111 (
b1001 /
b11111111111111111111111111111111 4
0=
b11111111111111111111111111101110 >
b11111111111111111111111111111111 ?
0K
0N
b11111111111111111111111111101110 Q
b001 R
b11111111111111111111111111111111 S
b0 ^
#380000000
1'
0*
13
06
1T
1W
1Z
1]
b0 _
#385000000
0'
03
0T
0W
0Z
0]
#390000000
b1010 #
b00000000000000000000000000010001 (
b1010 /
b00000000000000000000000000010001 4
1=
b01111111111111111111111111111011 >
b00000000000000000000000000010001 ?
1N
b01111111111111111111111111111011 Q
b010 R
b00000000000000000000000000010001 S
#395000000
1'
13
1T
1W
1Z
1]
#400000000
0'
03
0T
0W
0Z
0]
#405000000
b1011 #
b00000000000000000000000000000000 (
b1011 /
b00000000000000000000000000000000 4
0=
b11111111111111111111111111101110 >
b00000000000000000000000000000000 ?
1K
0N
b11111111111111111111111111101110 Q
b011 R
b00000000000000000000000000000000 S
b1 ^
#410000000
1'
1*
13
16
1T
1W
1Z
1]
b1 _
#415000000
0'
03
0T
0W
0Z
0]
#420000000
b1100 #
b1100 /
1=
b01111111111111111111111111111011 >
1N
b01111111111111111111111111111011 Q
b100 R
#425000000
1'
13
1T
1W
1Z
1]
#430000000
0'
03
0T
0W
0Z
0]
#435000000
b1101 #
b11111111111111111111111111111111 (
b1101 /
b11111111111111111111111111111111 4
0=
b11111111111111111111111111101110 >
b11111111111111111111111111111111 ?
0K
0N
b11111111111111111111111111101110 Q
b101 R
b11111111111111111111111111111111 S
b0 ^
#440000000
1'
0*
13
06
1T
1W
1Z
1]
b0 _
#445000000
0'
03
0T
0W
0Z
0]
#450000000
b1110 #
b01111111111111111111111111111011 (
b1110 /
b01111111111111111111111111111011 4
1=
b01111111111111111111111111111011 >
b01111111111111111111111111111011 ?
1N
b01111111111111111111111111111011 Q
b110 R
b01111111111111111111111111111011 S
#455000000
1'
13
1T
1W
1Z
1]
#460000000
0'
03
0T
0W
0Z
0]
#465000000
b1111 #
b11111111111111111111111111101110 (
b1111 /
b11111111111111111111111111101110 4
0=
b11111111111111111111111111101110 >
b11111111111111111111111111101110 ?
0N
b11111111111111111111111111101110 Q
b111 R
b11111111111111111111111111101110 S
#470000000
1'
13
1T
1W
1Z
1]
#475000000
0'
03
0T
0W
0Z
0]
